n2k/__init__.py
n2k/can_message.py
n2k/can_message_buffer.py
n2k/can_tools.py
n2k/constants.py
n2k/device.py
n2k/device_information.py
n2k/device_list.py
n2k/group_function.py
n2k/group_function_default_handlers.py
n2k/maretron.py
n2k/message.py
n2k/message_handler.py
n2k/messages.py
n2k/n2k.py
n2k/nmea2000_std_types.py
n2k/node.py
n2k/stream.py
n2k/types.py
n2k/utils.py
n2k-0.5.0.dist-info/licenses/LICENSE.txt
n2k-0.5.0.dist-info/METADATA
n2k-0.5.0.dist-info/WHEEL
n2k-0.5.0.dist-info/top_level.txt
n2k-0.5.0.dist-info/RECORD
